jobscrapers/__init__.py
jobscrapers/scrapers.py
jobscrapers-0.0.7.dist-info/licenses/LICENSE
jobscrapers-0.0.7.dist-info/METADATA
jobscrapers-0.0.7.dist-info/WHEEL
jobscrapers-0.0.7.dist-info/top_level.txt
jobscrapers-0.0.7.dist-info/RECORD
