Metadata-Version: 2.4
Name: jobscrapers
Version: 0.0.7
Summary: A package to scrape job postings.
Author-email: Mika <mikacchang@gmail.com>
Project-URL: Homepage, https://github.com/Mika-Chang/job-scrape
Project-URL: Issues, https://github.com/Mika-Chang/job-scrape/issues
Classifier: Programming Language :: Python :: 3
Classifier: Operating System :: OS Independent
Classifier: License :: OSI Approved :: GNU General Public License v3 (GPLv3)
Requires-Python: >=3.11
License-File: LICENSE
Requires-Dist: bs4~=0.0.2
Requires-Dist: requests~=2.32.3
Requires-Dist: selenium~=4.29.0
Dynamic: license-file
